setup.py
mypip22642.egg-info/PKG-INFO
mypip22642.egg-info/SOURCES.txt
mypip22642.egg-info/dependency_links.txt
mypip22642.egg-info/top_level.txt
sudok/__init__.py