Metadata-Version: 1.0
Name: mypip22642
Version: 0.0.1
Summary: A very basic calculator
Home-page: UNKNOWN
Author: UNKNOWN
Author-email: UNKNOWN
License: UNKNOWN
Platform: UNKNOWN
